{
    "@context": "http://www.shared-canvas.org/ns/context.json",
    "@id": "https://raw.githubusercontent.com/nakamura196/omekac_diyhistory/master/docs/oa/items/186/annolist.json",
    "@type": "sc:AnnotationList",
    "resources": [
        {
            "@context": "http://iiif.io/api/presentation/2/context.json",
            "@id": "https://diyhistory.org/public/omekac/oa/items/2438/anno.json",
            "@type": "oa:Annotation",
            "motivation": "oa:commenting",
            "on": [
                {
                    "@type": "oa:SpecificResource",
                    "full": "https://iiif.dl.itc.u-tokyo.ac.jp/repo/iiif/2c9e47b9-821a-42e1-84ed-9457929e7c7c/canvas/p57",
                    "selector": {
                        "@type": "oa:Choice",
                        "default": {
                            "@type": "oa:FragmentSelector",
                            "value": "xywh=3735,552,2807,2434"
                        },
                        "item": {
                            "@type": "oa:SvgSelector",
                            "value": "<svg xmlns='http://www.w3.org/2000/svg'><path xmlns=\"http://www.w3.org/2000/svg\" d=\"M6542.29089,2985.63611h-1403.57135v0h-1403.57135v-1216.81394v-1216.81394h1403.57135h1403.57135v1216.81394z\" data-paper-data=\"{&quot;strokeWidth&quot;:1,&quot;rotation&quot;:0,&quot;deleteIcon&quot;:null,&quot;rotationIcon&quot;:null,&quot;group&quot;:null,&quot;editable&quot;:true,&quot;annotation&quot;:null}\" id=\"rectangle_25efd98e-b93e-4c2e-9442-a0d46c7ee37a\" fill-opacity=\"0\" fill=\"#00bfff\" fill-rule=\"nonzero\" stroke=\"#00bfff\" stroke-width=\"1\" stroke-linecap=\"butt\" stroke-linejoin=\"miter\" stroke-miterlimit=\"10\" stroke-dasharray=\"\" stroke-dashoffset=\"0\" font-family=\"none\" font-weight=\"none\" font-size=\"none\" text-anchor=\"none\" style=\"mix-blend-mode: normal\"/></svg>"
                        }
                    },
                    "within": {
                        "@id": "https://raw.githubusercontent.com/nakamura196/omekac_diyhistory/master/docs/oa/collections/3/manifest.json",
                        "@type": "sc:Manifest"
                    }
                }
            ],
            "resource": [
                {
                    "@type": "dctypes:Text",
                    "chars": "<p>16-A00-6010-15-134</p>",
                    "format": "text/html"
                }
            ]
        },
        {
            "@context": "http://iiif.io/api/presentation/2/context.json",
            "@id": "https://diyhistory.org/public/omekac/oa/items/2439/anno.json",
            "@type": "oa:Annotation",
            "motivation": "oa:commenting",
            "on": [
                {
                    "@type": "oa:SpecificResource",
                    "full": "https://iiif.dl.itc.u-tokyo.ac.jp/repo/iiif/2c9e47b9-821a-42e1-84ed-9457929e7c7c/canvas/p57",
                    "selector": {
                        "@type": "oa:Choice",
                        "default": {
                            "@type": "oa:FragmentSelector",
                            "value": "xywh=903,552,2558,3554"
                        },
                        "item": {
                            "@type": "oa:SvgSelector",
                            "value": "<svg xmlns='http://www.w3.org/2000/svg'><path xmlns=\"http://www.w3.org/2000/svg\" d=\"M3460.79363,4106.18057h-1279.06641v0h-1279.06641v-1777.08617v-1777.08617h1279.06641h1279.06641v1777.08617z\" data-paper-data=\"{&quot;strokeWidth&quot;:1,&quot;rotation&quot;:0,&quot;deleteIcon&quot;:null,&quot;rotationIcon&quot;:null,&quot;group&quot;:null,&quot;editable&quot;:true,&quot;annotation&quot;:null}\" id=\"rectangle_c6dea161-8aea-46db-b560-41518a18f251\" fill-opacity=\"0\" fill=\"#00bfff\" fill-rule=\"nonzero\" stroke=\"#00bfff\" stroke-width=\"1\" stroke-linecap=\"butt\" stroke-linejoin=\"miter\" stroke-miterlimit=\"10\" stroke-dasharray=\"\" stroke-dashoffset=\"0\" font-family=\"none\" font-weight=\"none\" font-size=\"none\" text-anchor=\"none\" style=\"mix-blend-mode: normal\"/></svg>"
                        }
                    },
                    "within": {
                        "@id": "https://diyhistory.org/public/omekac/oa/collections/3/manifest.json",
                        "@type": "sc:Manifest"
                    }
                }
            ],
            "resource": [
                {
                    "@type": "dctypes:Text",
                    "chars": "<p>16-A00-6010-15-136</p>",
                    "format": "text/html"
                }
            ]
        },
        {
            "@context": "http://iiif.io/api/presentation/2/context.json",
            "@id": "https://diyhistory.org/public/omekac/oa/items/2440/anno.json",
            "@type": "oa:Annotation",
            "motivation": "oa:commenting",
            "on": [
                {
                    "@type": "oa:SpecificResource",
                    "full": "https://iiif.dl.itc.u-tokyo.ac.jp/repo/iiif/2c9e47b9-821a-42e1-84ed-9457929e7c7c/canvas/p57",
                    "selector": {
                        "@type": "oa:Choice",
                        "default": {
                            "@type": "oa:FragmentSelector",
                            "value": "xywh=3852,2949,2620,1951"
                        },
                        "item": {
                            "@type": "oa:SvgSelector",
                            "value": "<svg xmlns='http://www.w3.org/2000/svg'><path xmlns=\"http://www.w3.org/2000/svg\" d=\"M6472.25686,4899.89956h-1310.19265v0h-1310.19265v-975.58562v-975.58562h1310.19265h1310.19265v975.58562z\" data-paper-data=\"{&quot;strokeWidth&quot;:1,&quot;rotation&quot;:0,&quot;deleteIcon&quot;:null,&quot;rotationIcon&quot;:null,&quot;group&quot;:null,&quot;editable&quot;:true,&quot;annotation&quot;:null}\" id=\"rectangle_d6a5b5ad-556d-4eff-adfe-cf4b7c61c85e\" fill-opacity=\"0\" fill=\"#00bfff\" fill-rule=\"nonzero\" stroke=\"#00bfff\" stroke-width=\"1\" stroke-linecap=\"butt\" stroke-linejoin=\"miter\" stroke-miterlimit=\"10\" stroke-dasharray=\"\" stroke-dashoffset=\"0\" font-family=\"none\" font-weight=\"none\" font-size=\"none\" text-anchor=\"none\" style=\"mix-blend-mode: normal\"/></svg>"
                        }
                    },
                    "within": {
                        "@id": "https://diyhistory.org/public/omekac/oa/collections/3/manifest.json",
                        "@type": "sc:Manifest"
                    }
                }
            ],
            "resource": [
                {
                    "@type": "dctypes:Text",
                    "chars": "<p>16-A00-6010-15-135</p>",
                    "format": "text/html"
                }
            ]
        },
        {
            "@context": "http://iiif.io/api/presentation/2/context.json",
            "@id": "https://diyhistory.org/public/omekac/oa/items/2446/anno.json",
            "@type": "oa:Annotation",
            "motivation": "oa:commenting",
            "on": [
                {
                    "@type": "oa:SpecificResource",
                    "full": "https://iiif.dl.itc.u-tokyo.ac.jp/repo/iiif/2c9e47b9-821a-42e1-84ed-9457929e7c7c/canvas/p57",
                    "selector": {
                        "@type": "oa:Choice",
                        "default": {
                            "@type": "oa:FragmentSelector",
                            "value": "xywh=903,4116,1134,745"
                        },
                        "item": {
                            "@type": "oa:SvgSelector",
                            "value": "<svg xmlns='http://www.w3.org/2000/svg'><path xmlns=\"http://www.w3.org/2000/svg\" d=\"M2036.76839,4860.99177h-567.05379v0h-567.05379v-372.51482v-372.51482h567.05379h567.05379v372.51482z\" data-paper-data=\"{&quot;strokeWidth&quot;:1,&quot;rotation&quot;:0,&quot;deleteIcon&quot;:null,&quot;rotationIcon&quot;:null,&quot;group&quot;:null,&quot;editable&quot;:true,&quot;annotation&quot;:null}\" id=\"rectangle_0284ce94-5c8a-493d-8bc1-94f3f290c42f\" fill-opacity=\"0\" fill=\"#00bfff\" fill-rule=\"nonzero\" stroke=\"#00bfff\" stroke-width=\"1\" stroke-linecap=\"butt\" stroke-linejoin=\"miter\" stroke-miterlimit=\"10\" stroke-dasharray=\"\" stroke-dashoffset=\"0\" font-family=\"none\" font-weight=\"none\" font-size=\"none\" text-anchor=\"none\" style=\"mix-blend-mode: normal\"/></svg>"
                        }
                    },
                    "within": {
                        "@id": "https://diyhistory.org/public/omekac/oa/collections/3/manifest.json",
                        "@type": "sc:Manifest"
                    }
                }
            ],
            "resource": [
                {
                    "@type": "dctypes:Text",
                    "chars": "<p>16-A00-6010-15-139</p>",
                    "format": "text/html"
                }
            ]
        },
        {
            "@context": "http://iiif.io/api/presentation/2/context.json",
            "@id": "https://diyhistory.org/public/omekac/oa/items/2447/anno.json",
            "@type": "oa:Annotation",
            "motivation": "oa:commenting",
            "on": [
                {
                    "@type": "oa:SpecificResource",
                    "full": "https://iiif.dl.itc.u-tokyo.ac.jp/repo/iiif/2c9e47b9-821a-42e1-84ed-9457929e7c7c/canvas/p57",
                    "selector": {
                        "@type": "oa:Choice",
                        "default": {
                            "@type": "oa:FragmentSelector",
                            "value": "xywh=1961,4085,1033,815"
                        },
                        "item": {
                            "@type": "oa:SvgSelector",
                            "value": "<svg xmlns='http://www.w3.org/2000/svg'><path xmlns=\"http://www.w3.org/2000/svg\" d=\"M2993.90011,4899.89956h-516.47366v0h-516.47366v-407.53183v-407.53183h516.47366h516.47366v407.53183z\" data-paper-data=\"{&quot;strokeWidth&quot;:1,&quot;rotation&quot;:0,&quot;deleteIcon&quot;:null,&quot;rotationIcon&quot;:null,&quot;group&quot;:null,&quot;editable&quot;:true,&quot;annotation&quot;:null}\" id=\"rectangle_e504ef24-9019-43b3-9804-cfdfed47b127\" fill-opacity=\"0\" fill=\"#00bfff\" fill-rule=\"nonzero\" stroke=\"#00bfff\" stroke-width=\"1\" stroke-linecap=\"butt\" stroke-linejoin=\"miter\" stroke-miterlimit=\"10\" stroke-dasharray=\"\" stroke-dashoffset=\"0\" font-family=\"none\" font-weight=\"none\" font-size=\"none\" text-anchor=\"none\" style=\"mix-blend-mode: normal\"/></svg>"
                        }
                    },
                    "within": {
                        "@id": "https://diyhistory.org/public/omekac/oa/collections/3/manifest.json",
                        "@type": "sc:Manifest"
                    }
                }
            ],
            "resource": [
                {
                    "@type": "dctypes:Text",
                    "chars": "<p>16-A00-6010-15-138</p>",
                    "format": "text/html"
                }
            ]
        },
        {
            "@context": "http://iiif.io/api/presentation/2/context.json",
            "@id": "https://diyhistory.org/public/omekac/oa/items/2448/anno.json",
            "@type": "oa:Annotation",
            "motivation": "oa:commenting",
            "on": [
                {
                    "@type": "oa:SpecificResource",
                    "full": "https://iiif.dl.itc.u-tokyo.ac.jp/repo/iiif/2c9e47b9-821a-42e1-84ed-9457929e7c7c/canvas/p57",
                    "selector": {
                        "@type": "oa:Choice",
                        "default": {
                            "@type": "oa:FragmentSelector",
                            "value": "xywh=2949,4061,621,776"
                        },
                        "item": {
                            "@type": "oa:SvgSelector",
                            "value": "<svg xmlns='http://www.w3.org/2000/svg'><path xmlns=\"http://www.w3.org/2000/svg\" d=\"M3569.73546,4837.64709h-310.26235v0h-310.26235v-388.07794v-388.07794h310.26235h310.26235v388.07794z\" data-paper-data=\"{&quot;strokeWidth&quot;:1,&quot;rotation&quot;:0,&quot;deleteIcon&quot;:null,&quot;rotationIcon&quot;:null,&quot;group&quot;:null,&quot;editable&quot;:true,&quot;annotation&quot;:null}\" id=\"rectangle_b8d52e09-0b22-4cd2-a055-794667d21e13\" fill-opacity=\"0\" fill=\"#00bfff\" fill-rule=\"nonzero\" stroke=\"#00bfff\" stroke-width=\"1\" stroke-linecap=\"butt\" stroke-linejoin=\"miter\" stroke-miterlimit=\"10\" stroke-dasharray=\"\" stroke-dashoffset=\"0\" font-family=\"none\" font-weight=\"none\" font-size=\"none\" text-anchor=\"none\" style=\"mix-blend-mode: normal\"/></svg>"
                        }
                    },
                    "within": {
                        "@id": "https://diyhistory.org/public/omekac/oa/collections/3/manifest.json",
                        "@type": "sc:Manifest"
                    }
                }
            ],
            "resource": [
                {
                    "@type": "dctypes:Text",
                    "chars": "<p>16-A00-6010-15-137</p>",
                    "format": "text/html"
                }
            ]
        }
    ]
}