{
    "@context": "http://www.shared-canvas.org/ns/context.json",
    "@id": "https://raw.githubusercontent.com/nakamura196/omekac_diyhistory/master/docs/oa/items/12/annolist.json",
    "@type": "sc:AnnotationList",
    "resources": [
        {
            "@context": "http://iiif.io/api/presentation/2/context.json",
            "@id": "https://diyhistory.org/public/omekac/oa/items/1332/anno.json",
            "@type": "oa:Annotation",
            "motivation": "oa:commenting",
            "on": [
                {
                    "@type": "oa:SpecificResource",
                    "full": "https://iiif.dl.itc.u-tokyo.ac.jp/repo/iiif/64945590-996a-4b3b-876e-36b0662cf6dc/canvas/p12",
                    "selector": {
                        "@type": "oa:Choice",
                        "default": {
                            "@type": "oa:FragmentSelector",
                            "value": "xywh=2715,555,3229,2549"
                        },
                        "item": {
                            "@type": "oa:SvgSelector",
                            "value": "<svg xmlns='http://www.w3.org/2000/svg'><path xmlns=\"http://www.w3.org/2000/svg\" d=\"M5944.35565,3104.01756h-1614.61361v0h-1614.61361v-1274.2876v-1274.2876h1614.61361h1614.61361v1274.2876z\" data-paper-data=\"{&quot;strokeWidth&quot;:1,&quot;rotation&quot;:0,&quot;deleteIcon&quot;:null,&quot;rotationIcon&quot;:null,&quot;group&quot;:null,&quot;editable&quot;:true,&quot;annotation&quot;:null}\" id=\"rectangle_4760e065-6d20-4728-9ada-f9e566e41070\" fill-opacity=\"0\" fill=\"#00bfff\" fill-rule=\"nonzero\" stroke=\"#00bfff\" stroke-width=\"1\" stroke-linecap=\"butt\" stroke-linejoin=\"miter\" stroke-miterlimit=\"10\" stroke-dasharray=\"\" stroke-dashoffset=\"0\" font-family=\"none\" font-weight=\"none\" font-size=\"none\" text-anchor=\"none\" style=\"mix-blend-mode: normal\"/></svg>"
                        }
                    },
                    "within": {
                        "@id": "https://raw.githubusercontent.com/nakamura196/omekac_diyhistory/master/docs/oa/collections/1/manifest.json",
                        "@type": "sc:Manifest"
                    }
                }
            ],
            "resource": [
                {
                    "@type": "dctypes:Text",
                    "chars": "<p>16-A00-6010-2-30</p>",
                    "format": "text/html"
                }
            ]
        },
        {
            "@context": "http://iiif.io/api/presentation/2/context.json",
            "@id": "https://diyhistory.org/public/omekac/oa/items/1333/anno.json",
            "@type": "oa:Annotation",
            "motivation": "oa:commenting",
            "on": [
                {
                    "@type": "oa:SpecificResource",
                    "full": "https://iiif.dl.itc.u-tokyo.ac.jp/repo/iiif/64945590-996a-4b3b-876e-36b0662cf6dc/canvas/p12",
                    "selector": {
                        "@type": "oa:Choice",
                        "default": {
                            "@type": "oa:FragmentSelector",
                            "value": "xywh=800,563,1965,3887"
                        },
                        "item": {
                            "@type": "oa:SvgSelector",
                            "value": "<svg xmlns='http://www.w3.org/2000/svg'><path xmlns=\"http://www.w3.org/2000/svg\" d=\"M2765.48628,4450.36224h-982.57958v0h-982.57958v-1943.72009v-1943.72009h982.57958h982.57958v1943.72009z\" data-paper-data=\"{&quot;strokeWidth&quot;:1,&quot;rotation&quot;:0,&quot;deleteIcon&quot;:null,&quot;rotationIcon&quot;:null,&quot;group&quot;:null,&quot;editable&quot;:true,&quot;annotation&quot;:null}\" id=\"rectangle_f972c6de-33fc-44df-883f-ebafefc5bc50\" fill-opacity=\"0\" fill=\"#00bfff\" fill-rule=\"nonzero\" stroke=\"#00bfff\" stroke-width=\"1\" stroke-linecap=\"butt\" stroke-linejoin=\"miter\" stroke-miterlimit=\"10\" stroke-dasharray=\"\" stroke-dashoffset=\"0\" font-family=\"none\" font-weight=\"none\" font-size=\"none\" text-anchor=\"none\" style=\"mix-blend-mode: normal\"/></svg>"
                        }
                    },
                    "within": {
                        "@id": "https://diyhistory.org/public/omekac/oa/collections/1/manifest.json",
                        "@type": "sc:Manifest"
                    }
                }
            ],
            "resource": [
                {
                    "@type": "dctypes:Text",
                    "chars": "<p>16-A00-6010-2-31</p>",
                    "format": "text/html"
                }
            ]
        },
        {
            "@context": "http://iiif.io/api/presentation/2/context.json",
            "@id": "https://diyhistory.org/public/omekac/oa/items/1334/anno.json",
            "@type": "oa:Annotation",
            "motivation": "oa:commenting",
            "on": [
                {
                    "@type": "oa:SpecificResource",
                    "full": "https://iiif.dl.itc.u-tokyo.ac.jp/repo/iiif/64945590-996a-4b3b-876e-36b0662cf6dc/canvas/p12",
                    "selector": {
                        "@type": "oa:Choice",
                        "default": {
                            "@type": "oa:FragmentSelector",
                            "value": "xywh=5034,3099,933,1344"
                        },
                        "item": {
                            "@type": "oa:SvgSelector",
                            "value": "<svg xmlns='http://www.w3.org/2000/svg'><path xmlns=\"http://www.w3.org/2000/svg\" d=\"M5966.79473,4442.88255h-466.48079v0h-466.48079v-672.17234v-672.17234h466.48079h466.48079v672.17234z\" data-paper-data=\"{&quot;strokeWidth&quot;:1,&quot;rotation&quot;:0,&quot;deleteIcon&quot;:null,&quot;rotationIcon&quot;:null,&quot;group&quot;:null,&quot;editable&quot;:true,&quot;annotation&quot;:null}\" id=\"rectangle_8c1d5f02-0ee8-4510-b682-2654ac61bff7\" fill-opacity=\"0\" fill=\"#00bfff\" fill-rule=\"nonzero\" stroke=\"#00bfff\" stroke-width=\"1\" stroke-linecap=\"butt\" stroke-linejoin=\"miter\" stroke-miterlimit=\"10\" stroke-dasharray=\"\" stroke-dashoffset=\"0\" font-family=\"none\" font-weight=\"none\" font-size=\"none\" text-anchor=\"none\" style=\"mix-blend-mode: normal\"/></svg>"
                        }
                    },
                    "within": {
                        "@id": "https://diyhistory.org/public/omekac/oa/collections/1/manifest.json",
                        "@type": "sc:Manifest"
                    }
                }
            ],
            "resource": [
                {
                    "@type": "dctypes:Text",
                    "chars": "<p>16-A00-6010-2-32</p>",
                    "format": "text/html"
                }
            ]
        },
        {
            "@context": "http://iiif.io/api/presentation/2/context.json",
            "@id": "https://diyhistory.org/public/omekac/oa/items/1335/anno.json",
            "@type": "oa:Annotation",
            "motivation": "oa:commenting",
            "on": [
                {
                    "@type": "oa:SpecificResource",
                    "full": "https://iiif.dl.itc.u-tokyo.ac.jp/repo/iiif/64945590-996a-4b3b-876e-36b0662cf6dc/canvas/p12",
                    "selector": {
                        "@type": "oa:Choice",
                        "default": {
                            "@type": "oa:FragmentSelector",
                            "value": "xywh=4409,3263,619,1056"
                        },
                        "item": {
                            "@type": "oa:SvgSelector",
                            "value": "<svg xmlns='http://www.w3.org/2000/svg'><path xmlns=\"http://www.w3.org/2000/svg\" d=\"M4408.71053,3262.90906h309.60786v0h309.60786v528.0381v528.0381h-309.60786h-309.60786v-528.0381z\" data-paper-data=\"{&quot;strokeWidth&quot;:1,&quot;rotation&quot;:0,&quot;deleteIcon&quot;:null,&quot;rotationIcon&quot;:null,&quot;group&quot;:null,&quot;editable&quot;:true,&quot;annotation&quot;:null}\" id=\"rectangle_e8903817-ce4c-452b-8d1d-42a5f341d7eb\" fill-opacity=\"0\" fill=\"#00bfff\" fill-rule=\"nonzero\" stroke=\"#00bfff\" stroke-width=\"1\" stroke-linecap=\"butt\" stroke-linejoin=\"miter\" stroke-miterlimit=\"10\" stroke-dasharray=\"\" stroke-dashoffset=\"0\" font-family=\"none\" font-weight=\"none\" font-size=\"none\" text-anchor=\"none\" style=\"mix-blend-mode: normal\"/></svg>"
                        }
                    },
                    "within": {
                        "@id": "https://diyhistory.org/public/omekac/oa/collections/1/manifest.json",
                        "@type": "sc:Manifest"
                    }
                }
            ],
            "resource": [
                {
                    "@type": "dctypes:Text",
                    "chars": "<p>16-A00-6010-2-33</p>",
                    "format": "text/html"
                }
            ]
        },
        {
            "@context": "http://iiif.io/api/presentation/2/context.json",
            "@id": "https://diyhistory.org/public/omekac/oa/items/1336/anno.json",
            "@type": "oa:Annotation",
            "motivation": "oa:commenting",
            "on": [
                {
                    "@type": "oa:SpecificResource",
                    "full": "https://iiif.dl.itc.u-tokyo.ac.jp/repo/iiif/64945590-996a-4b3b-876e-36b0662cf6dc/canvas/p12",
                    "selector": {
                        "@type": "oa:Choice",
                        "default": {
                            "@type": "oa:FragmentSelector",
                            "value": "xywh=2786,3119,1609,1321"
                        },
                        "item": {
                            "@type": "oa:SvgSelector",
                            "value": "<svg xmlns='http://www.w3.org/2000/svg'><path xmlns=\"http://www.w3.org/2000/svg\" d=\"M2785.51334,3118.62486h804.58281v0h804.58281v660.29861v660.29861h-804.58281h-804.58281v-660.29861z\" data-paper-data=\"{&quot;strokeWidth&quot;:1,&quot;rotation&quot;:0,&quot;deleteIcon&quot;:null,&quot;rotationIcon&quot;:null,&quot;group&quot;:null,&quot;editable&quot;:true,&quot;annotation&quot;:null}\" id=\"rectangle_e7d0aeb8-6ffe-4d69-a948-f5aa556a9619\" fill-opacity=\"0\" fill=\"#00bfff\" fill-rule=\"nonzero\" stroke=\"#00bfff\" stroke-width=\"1\" stroke-linecap=\"butt\" stroke-linejoin=\"miter\" stroke-miterlimit=\"10\" stroke-dasharray=\"\" stroke-dashoffset=\"0\" font-family=\"none\" font-weight=\"none\" font-size=\"none\" text-anchor=\"none\" style=\"mix-blend-mode: normal\"/></svg>"
                        }
                    },
                    "within": {
                        "@id": "https://diyhistory.org/public/omekac/oa/collections/1/manifest.json",
                        "@type": "sc:Manifest"
                    }
                }
            ],
            "resource": [
                {
                    "@type": "dctypes:Text",
                    "chars": "<p>16-A00-6010-2-34</p>",
                    "format": "text/html"
                }
            ]
        }
    ]
}