{
    "@id": "https://diyhistory.org/public/omekac/api/1261.json",
    "added": "2018-10-28T08:41:28+00:00",
    "collection": null,
    "element_texts": [
        {
            "element": {
                "id": 50,
                "name": "Title",
                "resource": "elements",
                "url": "https://diyhistory.org/public/omekac/api/elements/50"
            },
            "element_set": {
                "id": 1,
                "name": "Dublin Core",
                "resource": "element_sets",
                "url": "https://diyhistory.org/public/omekac/api/element_sets/1"
            },
            "html": false,
            "text": "Annotation: \"16-A00-6010-14-28\""
        },
        {
            "element": {
                "id": 60,
                "name": "On Canvas",
                "resource": "elements",
                "url": "https://diyhistory.org/public/omekac/api/elements/60"
            },
            "element_set": {
                "id": 3,
                "name": "Item Type Metadata",
                "resource": "element_sets",
                "url": "https://diyhistory.org/public/omekac/api/element_sets/3"
            },
            "html": false,
            "text": "7d4d8665-f8ec-4c5a-83f9-82a01ad019ed"
        },
        {
            "element": {
                "id": 61,
                "name": "Selector",
                "resource": "elements",
                "url": "https://diyhistory.org/public/omekac/api/elements/61"
            },
            "element_set": {
                "id": 3,
                "name": "Item Type Metadata",
                "resource": "element_sets",
                "url": "https://diyhistory.org/public/omekac/api/element_sets/3"
            },
            "html": false,
            "text": "<svg xmlns='http://www.w3.org/2000/svg'><path xmlns=\"http://www.w3.org/2000/svg\" d=\"M6459.65487,4723.46018h-2707.03982v0h-2707.03982v-1928.08628v-1928.08628h2707.03982h2707.03982v1928.08628z\" data-paper-data=\"{&quot;strokeWidth&quot;:1,&quot;rotation&quot;:0,&quot;deleteIcon&quot;:null,&quot;rotationIcon&quot;:null,&quot;group&quot;:null,&quot;editable&quot;:true,&quot;annotation&quot;:null}\" id=\"rectangle_fc46495a-6b7e-4be1-8383-aeae72c47850\" fill-opacity=\"0\" fill=\"#00bfff\" fill-rule=\"nonzero\" stroke=\"#00bfff\" stroke-width=\"1\" stroke-linecap=\"butt\" stroke-linejoin=\"miter\" stroke-miterlimit=\"10\" stroke-dasharray=\"\" stroke-dashoffset=\"0\" font-family=\"none\" font-weight=\"none\" font-size=\"none\" text-anchor=\"none\" style=\"mix-blend-mode: normal\"/></svg>"
        },
        {
            "element": {
                "id": 62,
                "name": "Annotated Region",
                "resource": "elements",
                "url": "https://diyhistory.org/public/omekac/api/elements/62"
            },
            "element_set": {
                "id": 3,
                "name": "Item Type Metadata",
                "resource": "element_sets",
                "url": "https://diyhistory.org/public/omekac/api/element_sets/3"
            },
            "html": false,
            "text": "1046,867,5414,3856"
        },
        {
            "element": {
                "id": 1,
                "name": "Text",
                "resource": "elements",
                "url": "https://diyhistory.org/public/omekac/api/elements/1"
            },
            "element_set": {
                "id": 3,
                "name": "Item Type Metadata",
                "resource": "element_sets",
                "url": "https://diyhistory.org/public/omekac/api/element_sets/3"
            },
            "html": true,
            "text": "<p><span style=\"color: #333333; font-family: 'Open Sans', 'Lucida Grande', Verdana, Arial, sans-serif; background-color: #fafafa;\">16-A00-6010-14-28</span></p>"
        },
        {
            "element": {
                "id": 64,
                "name": "UUID",
                "resource": "elements",
                "url": "https://diyhistory.org/public/omekac/api/elements/64"
            },
            "element_set": {
                "id": 5,
                "name": "IIIF Item Metadata",
                "resource": "element_sets",
                "url": "https://diyhistory.org/public/omekac/api/element_sets/5"
            },
            "html": false,
            "text": "e2dda618-c7b1-418b-9f9c-ffb720cada27"
        },
        {
            "element": {
                "id": 55,
                "name": "Original @id",
                "resource": "elements",
                "url": "https://diyhistory.org/public/omekac/api/elements/55"
            },
            "element_set": {
                "id": 5,
                "name": "IIIF Item Metadata",
                "resource": "element_sets",
                "url": "https://diyhistory.org/public/omekac/api/element_sets/5"
            },
            "html": false,
            "text": "https://diyhistory.org/public/omekac/oa/items/1261/anno.json"
        },
        {
            "element": {
                "id": 56,
                "name": "JSON Data",
                "resource": "elements",
                "url": "https://diyhistory.org/public/omekac/api/elements/56"
            },
            "element_set": {
                "id": 5,
                "name": "IIIF Item Metadata",
                "resource": "element_sets",
                "url": "https://diyhistory.org/public/omekac/api/element_sets/5"
            },
            "html": false,
            "text": "{\"@context\":\"http://iiif.io/api/presentation/2/context.json\",\"@type\":\"oa:Annotation\",\"motivation\":\"oa:commenting\",\"resource\":[{\"@type\":\"dctypes:Text\",\"format\":\"text/html\",\"chars\":\"<p><span style=\\\"color: #333333; font-family: 'Open Sans', 'Lucida Grande', Verdana, Arial, sans-serif; background-color: #fafafa;\\\">16-A00-6010-14-28</span></p>\"}],\"on\":[{\"@type\":\"oa:SpecificResource\",\"full\":\"https://iiif.dl.itc.u-tokyo.ac.jp/repo/iiif/d31a5d15-afe1-411d-abaa-ed9263d5c800/canvas/p30\",\"selector\":{\"@type\":\"oa:Choice\",\"default\":{\"@type\":\"oa:FragmentSelector\",\"value\":\"xywh=1046,867,5414,3856\"},\"item\":{\"@type\":\"oa:SvgSelector\",\"value\":\"<svg xmlns='http://www.w3.org/2000/svg'><path xmlns=\\\"http://www.w3.org/2000/svg\\\" d=\\\"M6459.65487,4723.46018h-2707.03982v0h-2707.03982v-1928.08628v-1928.08628h2707.03982h2707.03982v1928.08628z\\\" data-paper-data=\\\"{&quot;strokeWidth&quot;:1,&quot;rotation&quot;:0,&quot;deleteIcon&quot;:null,&quot;rotationIcon&quot;:null,&quot;group&quot;:null,&quot;editable&quot;:true,&quot;annotation&quot;:null}\\\" id=\\\"rectangle_fc46495a-6b7e-4be1-8383-aeae72c47850\\\" fill-opacity=\\\"0\\\" fill=\\\"#00bfff\\\" fill-rule=\\\"nonzero\\\" stroke=\\\"#00bfff\\\" stroke-width=\\\"1\\\" stroke-linecap=\\\"butt\\\" stroke-linejoin=\\\"miter\\\" stroke-miterlimit=\\\"10\\\" stroke-dasharray=\\\"\\\" stroke-dashoffset=\\\"0\\\" font-family=\\\"none\\\" font-weight=\\\"none\\\" font-size=\\\"none\\\" text-anchor=\\\"none\\\" style=\\\"mix-blend-mode: normal\\\"/></svg>\"}},\"within\":{\"@id\":\"https://diyhistory.org/public/omekac/oa/collections/15/manifest.json\",\"@type\":\"sc:Manifest\"}}],\"@id\":\"https://diyhistory.org/public/omekac/oa/items/1261/anno.json\"}"
        }
    ],
    "extended_resources": {
        "exhibit_pages": {
            "count": 0,
            "resource": "exhibit_pages",
            "url": "https://diyhistory.org/public/omekac/api/exhibit_pages?item=1261"
        }
    },
    "featured": false,
    "files": {
        "count": 1,
        "resource": "files",
        "url": "https://diyhistory.org/public/omekac/api/files?item=1261"
    },
    "id": 1261,
    "item_type": {
        "id": 18,
        "name": "Annotation",
        "resource": "item_types",
        "url": "https://diyhistory.org/public/omekac/api/item_types/18"
    },
    "modified": "2020-08-31T07:26:06+00:00",
    "owner": {
        "id": 1,
        "resource": "users",
        "url": "https://diyhistory.org/public/omekac/api/users/1"
    },
    "public": true,
    "tags": [],
    "url": "https://diyhistory.org/public/omekac/api/items/1261"
}