{
    "@id": "https://diyhistory.org/public/omekac/api/32564.json",
    "added": "2020-07-13T10:22:00+00:00",
    "collection": null,
    "element_texts": [
        {
            "element": {
                "id": 50,
                "name": "Title",
                "resource": "elements",
                "url": "https://diyhistory.org/public/omekac/api/elements/50"
            },
            "element_set": {
                "id": 1,
                "name": "Dublin Core",
                "resource": "element_sets",
                "url": "https://diyhistory.org/public/omekac/api/element_sets/1"
            },
            "html": false,
            "text": "Annotation: \"中村寿々葉\""
        },
        {
            "element": {
                "id": 60,
                "name": "On Canvas",
                "resource": "elements",
                "url": "https://diyhistory.org/public/omekac/api/elements/60"
            },
            "element_set": {
                "id": 3,
                "name": "Item Type Metadata",
                "resource": "element_sets",
                "url": "https://diyhistory.org/public/omekac/api/element_sets/3"
            },
            "html": false,
            "text": "3a1a038a-10c9-43c0-9b4a-5cb3e9538ae6"
        },
        {
            "element": {
                "id": 61,
                "name": "Selector",
                "resource": "elements",
                "url": "https://diyhistory.org/public/omekac/api/elements/61"
            },
            "element_set": {
                "id": 3,
                "name": "Item Type Metadata",
                "resource": "element_sets",
                "url": "https://diyhistory.org/public/omekac/api/element_sets/3"
            },
            "html": false,
            "text": "<svg xmlns='http://www.w3.org/2000/svg'><path xmlns=\"http://www.w3.org/2000/svg\" d=\"M3988.71073,5157.80605h-721.23641v0h-721.23641v-949.55631v-949.55631h721.23641h721.23641v949.55631z\" data-paper-data=\"{&quot;strokeWidth&quot;:1,&quot;rotation&quot;:0,&quot;deleteIcon&quot;:null,&quot;rotationIcon&quot;:null,&quot;group&quot;:null,&quot;editable&quot;:true,&quot;annotation&quot;:null}\" id=\"rectangle_86e8c406-59ae-4393-afd0-22fa5eee4117\" fill-opacity=\"0\" fill=\"#00bfff\" fill-rule=\"nonzero\" stroke=\"#00bfff\" stroke-width=\"1\" stroke-linecap=\"butt\" stroke-linejoin=\"miter\" stroke-miterlimit=\"10\" stroke-dasharray=\"\" stroke-dashoffset=\"0\" font-family=\"none\" font-weight=\"none\" font-size=\"none\" text-anchor=\"none\" style=\"mix-blend-mode: normal\"/></svg>"
        },
        {
            "element": {
                "id": 62,
                "name": "Annotated Region",
                "resource": "elements",
                "url": "https://diyhistory.org/public/omekac/api/elements/62"
            },
            "element_set": {
                "id": 3,
                "name": "Item Type Metadata",
                "resource": "element_sets",
                "url": "https://diyhistory.org/public/omekac/api/element_sets/3"
            },
            "html": false,
            "text": "2546,3259,1442,1899"
        },
        {
            "element": {
                "id": 1,
                "name": "Text",
                "resource": "elements",
                "url": "https://diyhistory.org/public/omekac/api/elements/1"
            },
            "element_set": {
                "id": 3,
                "name": "Item Type Metadata",
                "resource": "element_sets",
                "url": "https://diyhistory.org/public/omekac/api/element_sets/3"
            },
            "html": true,
            "text": "<p>中村寿々葉</p>"
        },
        {
            "element": {
                "id": 64,
                "name": "UUID",
                "resource": "elements",
                "url": "https://diyhistory.org/public/omekac/api/elements/64"
            },
            "element_set": {
                "id": 5,
                "name": "IIIF Item Metadata",
                "resource": "element_sets",
                "url": "https://diyhistory.org/public/omekac/api/element_sets/5"
            },
            "html": false,
            "text": "fa9fe8f4-a275-480b-837d-7874156fc653"
        },
        {
            "element": {
                "id": 55,
                "name": "Original @id",
                "resource": "elements",
                "url": "https://diyhistory.org/public/omekac/api/elements/55"
            },
            "element_set": {
                "id": 5,
                "name": "IIIF Item Metadata",
                "resource": "element_sets",
                "url": "https://diyhistory.org/public/omekac/api/element_sets/5"
            },
            "html": false,
            "text": "https://diyhistory.org/public/omekac/oa/items/32564/anno.json"
        },
        {
            "element": {
                "id": 56,
                "name": "JSON Data",
                "resource": "elements",
                "url": "https://diyhistory.org/public/omekac/api/elements/56"
            },
            "element_set": {
                "id": 5,
                "name": "IIIF Item Metadata",
                "resource": "element_sets",
                "url": "https://diyhistory.org/public/omekac/api/element_sets/5"
            },
            "html": false,
            "text": "{\"@context\":\"http://iiif.io/api/presentation/2/context.json\",\"@type\":\"oa:Annotation\",\"motivation\":[\"oa:tagging\",\"oa:commenting\"],\"resource\":[{\"@type\":\"oa:Tag\",\"chars\":\"\\u798f\\u5ca1\\u770c\"},{\"@type\":\"oa:Tag\",\"chars\":\"\\u82b9\\u91ce\\u5fb3\\u4e09\\u90ce\"},{\"@type\":\"dctypes:Text\",\"format\":\"text/html\",\"chars\":\"<p>\\u4e2d\\u6751\\u5bff\\u3005\\u8449</p>\"}],\"on\":[{\"@type\":\"oa:SpecificResource\",\"full\":\"https://iiif.dl.itc.u-tokyo.ac.jp/repo/iiif/8ca2356e-ccde-4403-891e-c3817926a2ca/canvas/p12\",\"selector\":{\"@type\":\"oa:Choice\",\"default\":{\"@type\":\"oa:FragmentSelector\",\"value\":\"xywh=2546,3259,1442,1899\"},\"item\":{\"@type\":\"oa:SvgSelector\",\"value\":\"<svg xmlns='http://www.w3.org/2000/svg'><path xmlns=\\\"http://www.w3.org/2000/svg\\\" d=\\\"M3988.71073,5157.80605h-721.23641v0h-721.23641v-949.55631v-949.55631h721.23641h721.23641v949.55631z\\\" data-paper-data=\\\"{&quot;strokeWidth&quot;:1,&quot;rotation&quot;:0,&quot;deleteIcon&quot;:null,&quot;rotationIcon&quot;:null,&quot;group&quot;:null,&quot;editable&quot;:true,&quot;annotation&quot;:null}\\\" id=\\\"rectangle_86e8c406-59ae-4393-afd0-22fa5eee4117\\\" fill-opacity=\\\"0\\\" fill=\\\"#00bfff\\\" fill-rule=\\\"nonzero\\\" stroke=\\\"#00bfff\\\" stroke-width=\\\"1\\\" stroke-linecap=\\\"butt\\\" stroke-linejoin=\\\"miter\\\" stroke-miterlimit=\\\"10\\\" stroke-dasharray=\\\"\\\" stroke-dashoffset=\\\"0\\\" font-family=\\\"none\\\" font-weight=\\\"none\\\" font-size=\\\"none\\\" text-anchor=\\\"none\\\" style=\\\"mix-blend-mode: normal\\\"/></svg>\"}},\"within\":{\"@id\":\"https://diyhistory.org/public/omekac/oa/collections/82/manifest.json\",\"@type\":\"sc:Manifest\"}}],\"@id\":\"https://diyhistory.org/public/omekac/oa/items/32564/anno.json\"}"
        }
    ],
    "extended_resources": {
        "exhibit_pages": {
            "count": 0,
            "resource": "exhibit_pages",
            "url": "https://diyhistory.org/public/omekac/api/exhibit_pages?item=32564"
        }
    },
    "featured": false,
    "files": {
        "count": 0,
        "resource": "files",
        "url": "https://diyhistory.org/public/omekac/api/files?item=32564"
    },
    "id": 32564,
    "item_type": {
        "id": 18,
        "name": "Annotation",
        "resource": "item_types",
        "url": "https://diyhistory.org/public/omekac/api/item_types/18"
    },
    "modified": "2020-08-31T07:24:39+00:00",
    "owner": {
        "id": 2,
        "resource": "users",
        "url": "https://diyhistory.org/public/omekac/api/users/2"
    },
    "public": true,
    "tags": [
        {
            "id": 375,
            "name": "福岡県",
            "resource": "tags",
            "url": "https://diyhistory.org/public/omekac/api/tags/375"
        },
        {
            "id": 376,
            "name": "芹野徳三郎",
            "resource": "tags",
            "url": "https://diyhistory.org/public/omekac/api/tags/376"
        }
    ],
    "url": "https://diyhistory.org/public/omekac/api/items/32564"
}