{
    "@id": "https://diyhistory.org/public/omekac/api/41357.json",
    "added": "2020-10-17T07:38:27+00:00",
    "collection": null,
    "element_texts": [
        {
            "element": {
                "id": 50,
                "name": "Title",
                "resource": "elements",
                "url": "https://diyhistory.org/public/omekac/api/elements/50"
            },
            "element_set": {
                "id": 1,
                "name": "Dublin Core",
                "resource": "element_sets",
                "url": "https://diyhistory.org/public/omekac/api/element_sets/1"
            },
            "html": false,
            "text": "Annotation: \"S5W1(b)A3-21\""
        },
        {
            "element": {
                "id": 60,
                "name": "On Canvas",
                "resource": "elements",
                "url": "https://diyhistory.org/public/omekac/api/elements/60"
            },
            "element_set": {
                "id": 3,
                "name": "Item Type Metadata",
                "resource": "element_sets",
                "url": "https://diyhistory.org/public/omekac/api/element_sets/3"
            },
            "html": false,
            "text": "99a75eab-1379-44a2-b01a-3450990b14fe"
        },
        {
            "element": {
                "id": 61,
                "name": "Selector",
                "resource": "elements",
                "url": "https://diyhistory.org/public/omekac/api/elements/61"
            },
            "element_set": {
                "id": 3,
                "name": "Item Type Metadata",
                "resource": "element_sets",
                "url": "https://diyhistory.org/public/omekac/api/element_sets/3"
            },
            "html": false,
            "text": "<svg xmlns='http://www.w3.org/2000/svg'><path xmlns=\"http://www.w3.org/2000/svg\" d=\"M25622.76811,14322.49195l16.64777,7.62672v0l16.64777,7.62672l17.66024,-38.54919l17.66024,-38.54919l-16.64777,-7.62672l-16.64777,-7.62672l-17.66024,38.54919z\" data-paper-data=\"{&quot;strokeWidth&quot;:1,&quot;rotation&quot;:24.61357377076032,&quot;deleteIcon&quot;:null,&quot;rotationIcon&quot;:null,&quot;group&quot;:null,&quot;editable&quot;:true,&quot;annotation&quot;:null}\" id=\"rectangle_c09fa002-a98f-40f8-a92f-89bb9e0286cc\" fill-opacity=\"0\" fill=\"#00bfff\" fill-rule=\"nonzero\" stroke=\"#00bfff\" stroke-width=\"1\" stroke-linecap=\"butt\" stroke-linejoin=\"miter\" stroke-miterlimit=\"10\" stroke-dasharray=\"\" stroke-dashoffset=\"0\" font-family=\"none\" font-weight=\"none\" font-size=\"none\" text-anchor=\"none\" style=\"mix-blend-mode: normal\"/></svg>"
        },
        {
            "element": {
                "id": 62,
                "name": "Annotated Region",
                "resource": "elements",
                "url": "https://diyhistory.org/public/omekac/api/elements/62"
            },
            "element_set": {
                "id": 3,
                "name": "Item Type Metadata",
                "resource": "element_sets",
                "url": "https://diyhistory.org/public/omekac/api/element_sets/3"
            },
            "html": false,
            "text": "25623,14245,69,92"
        },
        {
            "element": {
                "id": 1,
                "name": "Text",
                "resource": "elements",
                "url": "https://diyhistory.org/public/omekac/api/elements/1"
            },
            "element_set": {
                "id": 3,
                "name": "Item Type Metadata",
                "resource": "element_sets",
                "url": "https://diyhistory.org/public/omekac/api/element_sets/3"
            },
            "html": true,
            "text": "<p>S5W1(b)A3-21</p>"
        },
        {
            "element": {
                "id": 64,
                "name": "UUID",
                "resource": "elements",
                "url": "https://diyhistory.org/public/omekac/api/elements/64"
            },
            "element_set": {
                "id": 5,
                "name": "IIIF Item Metadata",
                "resource": "element_sets",
                "url": "https://diyhistory.org/public/omekac/api/element_sets/5"
            },
            "html": false,
            "text": "2de31348-43c6-4b54-a956-b1cd6cfe38b6"
        },
        {
            "element": {
                "id": 55,
                "name": "Original @id",
                "resource": "elements",
                "url": "https://diyhistory.org/public/omekac/api/elements/55"
            },
            "element_set": {
                "id": 5,
                "name": "IIIF Item Metadata",
                "resource": "element_sets",
                "url": "https://diyhistory.org/public/omekac/api/element_sets/5"
            },
            "html": false,
            "text": "https://diyhistory.org/public/omekac/oa/items/41357/anno.json"
        },
        {
            "element": {
                "id": 56,
                "name": "JSON Data",
                "resource": "elements",
                "url": "https://diyhistory.org/public/omekac/api/elements/56"
            },
            "element_set": {
                "id": 5,
                "name": "IIIF Item Metadata",
                "resource": "element_sets",
                "url": "https://diyhistory.org/public/omekac/api/element_sets/5"
            },
            "html": false,
            "text": "{\"@context\":\"http://iiif.io/api/presentation/2/context.json\",\"@type\":\"oa:Annotation\",\"motivation\":\"oa:commenting\",\"resource\":[{\"@type\":\"dctypes:Text\",\"format\":\"text/html\",\"chars\":\"<p>S5W1(b)A3-21</p>\"}],\"on\":[{\"@type\":\"oa:SpecificResource\",\"full\":\"https://nakamura196.github.io/suikeichuuzu/iiif/main/canvas/p1\",\"selector\":{\"@type\":\"oa:Choice\",\"default\":{\"@type\":\"oa:FragmentSelector\",\"value\":\"xywh=25623,14245,69,92\"},\"item\":{\"@type\":\"oa:SvgSelector\",\"value\":\"<svg xmlns='http://www.w3.org/2000/svg'><path xmlns=\\\"http://www.w3.org/2000/svg\\\" d=\\\"M25622.76811,14322.49195l16.64777,7.62672v0l16.64777,7.62672l17.66024,-38.54919l17.66024,-38.54919l-16.64777,-7.62672l-16.64777,-7.62672l-17.66024,38.54919z\\\" data-paper-data=\\\"{&quot;strokeWidth&quot;:1,&quot;rotation&quot;:24.61357377076032,&quot;deleteIcon&quot;:null,&quot;rotationIcon&quot;:null,&quot;group&quot;:null,&quot;editable&quot;:true,&quot;annotation&quot;:null}\\\" id=\\\"rectangle_c09fa002-a98f-40f8-a92f-89bb9e0286cc\\\" fill-opacity=\\\"0\\\" fill=\\\"#00bfff\\\" fill-rule=\\\"nonzero\\\" stroke=\\\"#00bfff\\\" stroke-width=\\\"1\\\" stroke-linecap=\\\"butt\\\" stroke-linejoin=\\\"miter\\\" stroke-miterlimit=\\\"10\\\" stroke-dasharray=\\\"\\\" stroke-dashoffset=\\\"0\\\" font-family=\\\"none\\\" font-weight=\\\"none\\\" font-size=\\\"none\\\" text-anchor=\\\"none\\\" style=\\\"mix-blend-mode: normal\\\"/></svg>\"}},\"within\":{\"@id\":\"https://diyhistory.org/public/omekac/oa/collections/258/manifest.json\",\"@type\":\"sc:Manifest\"}}],\"@id\":\"https://diyhistory.org/public/omekac/oa/items/41357/anno.json\"}"
        }
    ],
    "extended_resources": {
        "exhibit_pages": {
            "count": 0,
            "resource": "exhibit_pages",
            "url": "https://diyhistory.org/public/omekac/api/exhibit_pages?item=41357"
        }
    },
    "featured": false,
    "files": {
        "count": 0,
        "resource": "files",
        "url": "https://diyhistory.org/public/omekac/api/files?item=41357"
    },
    "id": 41357,
    "item_type": {
        "id": 18,
        "name": "Annotation",
        "resource": "item_types",
        "url": "https://diyhistory.org/public/omekac/api/item_types/18"
    },
    "modified": "2020-10-28T22:53:08+00:00",
    "owner": {
        "id": 5,
        "resource": "users",
        "url": "https://diyhistory.org/public/omekac/api/users/5"
    },
    "public": true,
    "tags": [],
    "url": "https://diyhistory.org/public/omekac/api/items/41357"
}