{
    "@context": "http://www.shared-canvas.org/ns/context.json",
    "@id": "https://raw.githubusercontent.com/nakamura196/omekac_diyhistory/master/docs/oa/items/4801/annolist.json",
    "@type": "sc:AnnotationList",
    "resources": [
        {
            "@context": "http://iiif.io/api/presentation/2/context.json",
            "@id": "https://diyhistory.org/public/omekac/oa/items/4908/anno.json",
            "@type": "oa:Annotation",
            "motivation": "oa:commenting",
            "on": [
                {
                    "@type": "oa:SpecificResource",
                    "full": "https://diyhistory.org/public/dalab/iiif/23/canvas/p17",
                    "selector": {
                        "@type": "oa:Choice",
                        "default": {
                            "@type": "oa:FragmentSelector",
                            "value": "xywh=3121,3586,1854,74"
                        },
                        "item": {
                            "@type": "oa:SvgSelector",
                            "value": "<svg xmlns='http://www.w3.org/2000/svg'><path xmlns=\"http://www.w3.org/2000/svg\" d=\"M3121.26382,3586.24197h927.04174v0h927.04174v37.22067v37.22067h-927.04174h-927.04174v-37.22067z\" data-paper-data=\"{&quot;strokeWidth&quot;:1,&quot;rotation&quot;:0,&quot;deleteIcon&quot;:null,&quot;rotationIcon&quot;:null,&quot;group&quot;:null,&quot;editable&quot;:true,&quot;annotation&quot;:null}\" id=\"rectangle_890a4040-835c-4056-a6c3-3ddec0c98a56\" fill-opacity=\"0\" fill=\"#00bfff\" fill-rule=\"nonzero\" stroke=\"#00bfff\" stroke-width=\"1\" stroke-linecap=\"butt\" stroke-linejoin=\"miter\" stroke-miterlimit=\"10\" stroke-dasharray=\"\" stroke-dashoffset=\"0\" font-family=\"none\" font-weight=\"none\" font-size=\"none\" text-anchor=\"none\" style=\"mix-blend-mode: normal\"/></svg>"
                        }
                    },
                    "within": {
                        "@id": "http://diyhistory.org/public/omekac/oa/collections/26/manifest.json",
                        "@type": "sc:Manifest"
                    }
                }
            ],
            "resource": [
                {
                    "@type": "dctypes:Text",
                    "chars": "<p>（大正2年2月20日）神田大火の惨状</p>",
                    "format": "text/html"
                }
            ]
        }
    ]
}